rusmarkup
