Metadata-Version: 1.1
Name: rusmarkup
Version: 1.1.0
Summary: Простой язык разметки для русского языка
Home-page: https://github.com/maksimryndin/rusmarkup
Author: Maksim Ryndin
Author-email: maksim.ryndin@gmail.com
License: MIT
Platform: UNKNOWN
Classifier: Development Status :: 3 - Alpha
Classifier: Intended Audience :: Developers
Classifier: Natural Language :: Russian
Classifier: Programming Language :: Python
Classifier: Programming Language :: Python :: 3
Classifier: Programming Language :: Python :: 3.6
Classifier: Programming Language :: Python :: 3.7
Classifier: Programming Language :: Python :: Implementation :: CPython
Classifier: Programming Language :: Python :: Implementation :: PyPy
Classifier: Topic :: Software Development :: Libraries :: Python Modules
